pySDC/.DS_Store
pySDC/README.rst
pySDC/README_API.rst
pySDC/__init__.py
pySDC/core/__init__.py
pySDC/core/base_transfer.py
pySDC/core/collocation.py
pySDC/core/common.py
pySDC/core/controller.py
pySDC/core/convergence_controller.py
pySDC/core/errors.py
pySDC/core/hooks.py
pySDC/core/level.py
pySDC/core/problem.py
pySDC/core/space_transfer.py
pySDC/core/step.py
pySDC/core/sweeper.py
pySDC/helpers/NCCL_communicator.py
pySDC/helpers/__init__.py
pySDC/helpers/plot_helper.py
pySDC/helpers/problem_helper.py
pySDC/helpers/pysdc_helper.py
pySDC/helpers/setup_helper.py
pySDC/helpers/spectral_helper.py
pySDC/helpers/stats_helper.py
pySDC/helpers/testing.py
pySDC/helpers/transfer_helper.py
pySDC/helpers/visualization_tools.py
pySDC/implementations/__init__.py
pySDC/implementations/controller_classes/__init__.py
pySDC/implementations/controller_classes/controller_MPI.py
pySDC/implementations/controller_classes/controller_nonMPI.py
pySDC/implementations/convergence_controller_classes/__init__.py
pySDC/implementations/convergence_controller_classes/adaptive_collocation.py
pySDC/implementations/convergence_controller_classes/adaptivity.py
pySDC/implementations/convergence_controller_classes/basic_restarting.py
pySDC/implementations/convergence_controller_classes/check_convergence.py
pySDC/implementations/convergence_controller_classes/check_iteration_estimator.py
pySDC/implementations/convergence_controller_classes/crash.py
pySDC/implementations/convergence_controller_classes/estimate_contraction_factor.py
pySDC/implementations/convergence_controller_classes/estimate_embedded_error.py
pySDC/implementations/convergence_controller_classes/estimate_extrapolation_error.py
pySDC/implementations/convergence_controller_classes/estimate_polynomial_error.py
pySDC/implementations/convergence_controller_classes/hotrod.py
pySDC/implementations/convergence_controller_classes/inexactness.py
pySDC/implementations/convergence_controller_classes/interpolate_between_restarts.py
pysdc-5.5.2.dist-info/WHEEL
pysdc-5.5.2.dist-info/METADATA
pysdc-5.5.2.dist-info/RECORD
