Metadata-Version: 2.1
Name: pySDC
Version: 5.5.2
Summary: A Python implementation of spectral deferred correction methods and the likes
Author-email: Robert Speck <r.speck@fz-juelich.de>, Thibaut Lunet <thibaut.lunet@tuhh.de>, Thomas Baumann <t.baumann@fz-juelich.de>, Lisa Wimmer <wimmer@uni-wuppertal.de>, Ikrom Akramov <ikrom.akramov@tuhh.de>, Giacomo Rosilho De Souza <giacomo.rosilhodesouza@usi.ch>, Jakob Fritz <j.fritz@fz-juelich.de>
Classifier: Topic :: Scientific/Engineering :: Mathematics
Requires-Dist: numpy>=1.15.4
Requires-Dist: scipy>=0.17.1
Requires-Dist: matplotlib>=3.0
Requires-Dist: sympy>=1.0
Requires-Dist: numba>=0.35
Requires-Dist: dill>=0.2.6
Requires-Dist: qmat>=0.1.8
Requires-Dist: petsc4py>=3.10.0 ; extra == "apps"
Requires-Dist: mpi4py>=3.0.0 ; extra == "apps"
Requires-Dist: fenics>=2019.1.0 ; extra == "apps"
Requires-Dist: mpi4py-fft>=2.0.2 ; extra == "apps"
Requires-Dist: ruff ; extra == "dev"
Requires-Dist: pytest ; extra == "dev"
Requires-Dist: pytest-cov ; extra == "dev"
Requires-Dist: sphinx ; extra == "dev"
Project-URL: Documentation, http://www.parallel-in-time.org/pySDC/
Project-URL: Homepage, http://www.parallel-in-time.org/pySDC/
Project-URL: Repository, https://github.com/Parallel-in-Time/pySDC/
Project-URL: Tracker, https://github.com/Parallel-in-Time/pySDC/issues
Provides-Extra: apps
Provides-Extra: dev
